chordpro/__init__.py
chordpro/__main__.py
chordpro/base.py
chordpro/chords.py
chordpro/cli.py
chordpro/constants.py
chordpro/renderers/__init__.py
chordpro/renderers/html.py
chordpro/renderers/text.py
python_chordpro-0.0.2.dist-info/LICENSE
python_chordpro-0.0.2.dist-info/METADATA
python_chordpro-0.0.2.dist-info/WHEEL
python_chordpro-0.0.2.dist-info/entry_points.txt
python_chordpro-0.0.2.dist-info/top_level.txt
python_chordpro-0.0.2.dist-info/RECORD
