Metadata-Version: 2.1
Name: python-chordpro
Version: 0.0.2
Summary: A ChordPro parser, written in Python
Home-page: https://git.snyman.info/raoul/python-chordpro
Author: Raoul Snyman
Author-email: raoul@snyman.info
License: MIT
Keywords: music,chords,guitar
Platform: UNKNOWN
Classifier: Development Status :: 3 - Alpha
Classifier: Intended Audience :: Developers
Classifier: License :: OSI Approved :: MIT License
Classifier: Operating System :: POSIX
Classifier: Programming Language :: Python :: 3
Classifier: Programming Language :: Python :: 3.7
Classifier: Programming Language :: Python :: 3.8
Classifier: Programming Language :: Python :: 3.9
Classifier: Programming Language :: Python :: 3.10
Classifier: Topic :: Utilities
Requires-Python: >=3.7
License-File: LICENSE
Requires-Dist: pyhyphen
